MANIFEST.in
README.md
lxd_exporter.py
lxd_exporter.egg-info/PKG-INFO
lxd_exporter.egg-info/SOURCES.txt
lxd_exporter.egg-info/dependency_links.txt
lxd_exporter.egg-info/entry_points.txt
lxd_exporter.egg-info/requires.txt
lxd_exporter.egg-info/top_level.txt
lxd_exporter-0.4.8.dist-info/METADATA
lxd_exporter-0.4.8.dist-info/WHEEL
lxd_exporter-0.4.8.dist-info/entry_points.txt
lxd_exporter-0.4.8.dist-info/top_level.txt
lxd_exporter-0.4.8.dist-info/RECORD
